{
  "kind": "collectionType",
  "collectionName": "products",
  "info": {
    "singularName": "product",
    "pluralName": "products",
    "displayName": "Product"
  },
  "options": {
    "draftAndPublish": true
  },
  "pluginOptions": {},
  "attributes": {
    "title": {
      "type": "string"
    },
    "slug": {
      "type": "uid"
    },
    "description": {
      "type": "blocks"
    },
    "price": {
      "type": "decimal"
    },
    "stock": {
      "type": "integer"
    },
    "isActive": {
      "type": "boolean"
    },
    "mainImage": {
      "type": "media",
      "multiple": false,
      "allowedTypes": [
        "images",
        "files",
        "videos",
        "audios"
      ]
    },
    "categories": {
      "type": "relation",
      "relation": "oneToMany",
      "target": "api::category.category",
      "mappedBy": "product"
    },
    "product_image": {
      "type": "relation",
      "relation": "manyToOne",
      "target": "api::product-image.product-image",
      "inversedBy": "products"
    },
    "order_item": {
      "type": "relation",
      "relation": "oneToOne",
      "target": "api::order-item.order-item",
      "mappedBy": "product"
    }
  }
}
